setup.py
sk_gaussian_binomial_distributions/Binomialdistribution.py
sk_gaussian_binomial_distributions/Gaussiandistribution.py
sk_gaussian_binomial_distributions/Generaldistribution.py
sk_gaussian_binomial_distributions/__init__.py
sk_gaussian_binomial_distributions.egg-info/PKG-INFO
sk_gaussian_binomial_distributions.egg-info/SOURCES.txt
sk_gaussian_binomial_distributions.egg-info/dependency_links.txt
sk_gaussian_binomial_distributions.egg-info/not-zip-safe
sk_gaussian_binomial_distributions.egg-info/top_level.txt