Metadata-Version: 2.1
Name: sk-gaussian-binomial-distributions
Version: 0.1
Summary: Gaussian and Binomial distributions
Author: Spyros Karydis
